terraform_models/__init__.py
terraform_models/vsphere.py
terraform_models-0.1.0.dist-info/METADATA
terraform_models-0.1.0.dist-info/WHEEL
terraform_models-0.1.0.dist-info/RECORD
