Metadata-Version: 2.1
Name: terraform-models
Version: 0.1.0
Summary: 
Author: Daniel
Author-email: dshaal@paloaltonetworks.com
Requires-Python: >=3.9,<4.0
Classifier: Programming Language :: Python :: 3
Classifier: Programming Language :: Python :: 3.9
Classifier: Programming Language :: Python :: 3.10
Classifier: Programming Language :: Python :: 3.11
Classifier: Programming Language :: Python :: 3.12
Classifier: Programming Language :: Python :: 3.13
Requires-Dist: pydantic (>=2.11.3,<3.0.0)
